cotton_heroicons/__init__.py
cotton_heroicons/apps.py
cotton_heroicons/templates/cotton/heroicon/academic_cap.html
cotton_heroicons/templates/cotton/heroicon/adjustments_horizontal.html
cotton_heroicons/templates/cotton/heroicon/adjustments_vertical.html
cotton_heroicons/templates/cotton/heroicon/archive_box.html
cotton_heroicons/templates/cotton/heroicon/archive_box_arrow_down.html
cotton_heroicons/templates/cotton/heroicon/archive_box_x_mark.html
cotton_heroicons/templates/cotton/heroicon/arrow_down.html
cotton_heroicons/templates/cotton/heroicon/arrow_down_circle.html
cotton_heroicons/templates/cotton/heroicon/arrow_down_left.html
cotton_heroicons/templates/cotton/heroicon/arrow_down_on_square.html
cotton_heroicons/templates/cotton/heroicon/arrow_down_on_square_stack.html
cotton_heroicons/templates/cotton/heroicon/arrow_down_right.html
cotton_heroicons/templates/cotton/heroicon/arrow_down_tray.html
cotton_heroicons/templates/cotton/heroicon/arrow_left.html
cotton_heroicons/templates/cotton/heroicon/arrow_left_circle.html
cotton_heroicons/templates/cotton/heroicon/arrow_left_end_on_rectangle.html
cotton_heroicons/templates/cotton/heroicon/arrow_left_start_on_rectangle.html
cotton_heroicons/templates/cotton/heroicon/arrow_long_down.html
cotton_heroicons/templates/cotton/heroicon/arrow_long_left.html
cotton_heroicons/templates/cotton/heroicon/arrow_long_right.html
cotton_heroicons/templates/cotton/heroicon/arrow_long_up.html
cotton_heroicons/templates/cotton/heroicon/arrow_path.html
cotton_heroicons/templates/cotton/heroicon/arrow_path_rounded_square.html
cotton_heroicons/templates/cotton/heroicon/arrow_right.html
cotton_heroicons/templates/cotton/heroicon/arrow_right_circle.html
cotton_heroicons/templates/cotton/heroicon/arrow_right_end_on_rectangle.html
cotton_heroicons/templates/cotton/heroicon/arrow_right_start_on_rectangle.html
cotton_heroicons/templates/cotton/heroicon/arrow_top_right_on_square.html
cotton_heroicons-0.1.2.dist-info/METADATA
cotton_heroicons-0.1.2.dist-info/WHEEL
cotton_heroicons-0.1.2.dist-info/licenses/LICENSE
cotton_heroicons-0.1.2.dist-info/RECORD
