Metadata-Version: 2.4
Name: cotton-heroicons
Version: 0.1.2
Summary: A Django Cotton Component Library of Heroicons
Project-URL: Homepage, https://github.com/snopoke/cotton-heroicons
License-Expression: MIT
License-File: LICENSE
Keywords: component,cotton,django,heroicons,library
Classifier: License :: OSI Approved :: MIT License
Classifier: Operating System :: OS Independent
Classifier: Programming Language :: Python :: 3
Requires-Python: >=3.8
Requires-Dist: django-cotton>=1.2.1
Requires-Dist: django>=4.2
